keep_it_secret/__init__.py
keep_it_secret/ext/__init__.py
keep_it_secret/ext/aws.py
keep_it_secret/ext/loader.py
keep_it_secret/ext/vault.py
keep_it_secret/fields.py
keep_it_secret/py.typed
keep_it_secret/secrets.py
keep_it_secret-1.2.0.dist-info/LICENSE
keep_it_secret-1.2.0.dist-info/METADATA
keep_it_secret-1.2.0.dist-info/WHEEL
keep_it_secret-1.2.0.dist-info/RECORD
