Metadata-Version: 2.1
Name: keep-it-secret
Version: 1.2.0
Summary: Keep It Secret by BTHLabs
Home-page: https://projects.bthlabs.pl/keep-it-secret/
License: MIT
Author: Tomek Wójcik
Author-email: contact@bthlabs.pl
Maintainer: BTHLabs
Maintainer-email: contact@bthlabs.pl
Requires-Python: >=3.10,<4.0
Classifier: License :: OSI Approved :: MIT License
Classifier: Programming Language :: Python :: 3
Classifier: Programming Language :: Python :: 3.10
Classifier: Programming Language :: Python :: 3.11
Classifier: Programming Language :: Python :: 3.12
Provides-Extra: aws
Provides-Extra: vault
Requires-Dist: boto3 (>=1.34.0) ; extra == "aws"
Requires-Dist: hvac (>=2.1.0) ; extra == "vault"
Project-URL: Documentation, https://projects.bthlabs.pl/keep-it-secret/
Project-URL: Repository, https://git.bthlabs.pl/tomekwojcik/keep-it-secret/
